[
  {
    "text": "這個模板的核心概念是：場景導向。",
    "startTime": 0,
    "endTime": 3
  },
  {
    "text": "每支影片可以拆成三個場景——開場、主內容、結尾。",
    "startTime": 3,
    "endTime": 7.3
  },
  {
    "text": "開場就是封面和 Hook，主內容是今天要講的東西，結尾是重點回顧跟訂閱提醒。",
    "startTime": 7.3,
    "endTime": 13.18
  },
  {
    "text": "每種場景有它固定的版面和節奏，但內容是可以抽換的。",
    "startTime": 13.18,
    "endTime": 17.56
  },
  {
    "text": "這樣我只需要專注在『寫腳本』這件事，其他技術細節模板都會處理。",
    "startTime": 17.56,
    "endTime": 25.1
  },
  {
    "text": "另一個關鍵是：資料驅動。",
    "startTime": 25.1,
    "endTime": 27.04
  },
  {
    "text": "所有的內容——標題、講稿、時間長度——都放在一個設定檔裡。",
    "startTime": 27.04,
    "endTime": 32.4
  },
  {
    "text": "我只要改這個檔案，然後跑一個指令生成語音，影片就會自動更新。",
    "startTime": 32.4,
    "endTime": 37.12
  },
  {
    "text": "對工程師來說，這就像是把影片當成一個 App 來開發：內容是資料，模板是程式邏輯，輸出是影片。",
    "startTime": 37.12,
    "endTime": 44.28
  },
  {
    "text": "分離關注點，維護起來輕鬆很多。",
    "startTime": 44.28,
    "endTime": 47.28
  }
]